yotool/__init__.py
yotool/config/__init__.py
yotool/config/configuer.py
yotool/cuda/__init__.py
yotool/cuda/deviceutils.py
yotool/run/__init__.py
yotool/run/run.py
yotool/util/__init__.py
yotool/util/logger.py
yotool-0.1.2.dist-info/LICENSE.txt
yotool-0.1.2.dist-info/METADATA
yotool-0.1.2.dist-info/WHEEL
yotool-0.1.2.dist-info/top_level.txt
yotool-0.1.2.dist-info/RECORD
