Metadata-Version: 2.1
Name: yotool
Version: 0.1.2
Summary: A smart tool for deep learning with Pytorch
Author: Qing Yao
License: MIT
Keywords: tool,Pytorch
Classifier: Development Status :: 3 - Alpha
Classifier: Intended Audience :: Developers
Classifier: Topic :: Software Development :: Build Tools
Classifier: License :: OSI Approved :: MIT License
Classifier: Programming Language :: Python :: 3
License-File: LICENSE.txt
Requires-Dist: pynvml (>=11.5.0)
Requires-Dist: torch (>=1.8.0)
